basis/__init__.py
basis/character_container.py
basis/token_container.py
basis/utils.py
basis/word_container.py
basis-0.1.0.dist-info/DESCRIPTION.rst
basis-0.1.0.dist-info/METADATA
basis-0.1.0.dist-info/RECORD
basis-0.1.0.dist-info/WHEEL
basis-0.1.0.dist-info/metadata.json
basis-0.1.0.dist-info/top_level.txt
